disfs/__init__.py
disfs/auth.py
disfs/cli.py
disfs/crypto.py
disfs/discord.py
disfs/file.py
disfs/fs.py
disfs/utils.py
disfs-0.1.2.dist-info/entry_points.txt
disfs-0.1.2.dist-info/WHEEL
disfs-0.1.2.dist-info/METADATA
disfs-0.1.2.dist-info/RECORD
