Metadata-Version: 2.1
Name: disfs
Version: 0.1.2
Summary: Discord-based filesystem
Author: witherornot
Requires-Python: >=3.7,<4.0
Classifier: Programming Language :: Python :: 3
Classifier: Programming Language :: Python :: 3.10
Classifier: Programming Language :: Python :: 3.7
Classifier: Programming Language :: Python :: 3.8
Classifier: Programming Language :: Python :: 3.9
Requires-Dist: config-path (>=1.0.2,<2.0.0)
Requires-Dist: keyring (>=21.2.0,<22.0.0)
Requires-Dist: pycryptodome (>=3.12.0,<4.0.0)
Requires-Dist: requests (>=2.27.1,<3.0.0)
Requires-Dist: requests-toolbelt (>=0.9.1,<0.10.0)
Requires-Dist: tqdm (>=4.62.3,<5.0.0)
